{
  "osservazioni": {
    "palestra": {
      "lun": [
        {
          "ora": "17:30",
          "fonte": "keyword",
          "data": "2026-03-09"
        }
      ],
      "mar": [
        {
          "ora": "21:50",
          "fonte": "keyword",
          "data": "2026-03-10"
        },
        {
          "ora": "21:51",
          "fonte": "keyword",
          "data": "2026-03-17"
        }
      ],
      "gio": [
        {
          "ora": "17:27",
          "fonte": "gap+schermo",
          "data": "2026-03-12"
        }
      ]
    },
    "studio": {
      "mar": [
        {
          "ora": "17:26",
          "fonte": "keyword",
          "data": "2026-03-10"
        }
      ]
    },
    "uscita": {
      "mar": [
        {
          "ora": "17:26",
          "fonte": "gap+schermo",
          "data": "2026-03-10"
        },
        {
          "ora": "22:33",
          "fonte": "keyword",
          "data": "2026-03-10"
        }
      ],
      "gio": [
        {
          "ora": "16:51",
          "fonte": "keyword",
          "data": "2026-03-12"
        },
        {
          "ora": "15:06",
          "fonte": "gap+calendario+schermo",
          "data": "2026-03-12"
        }
      ]
    },
    "rientro": {
      "gio": [
        {
          "ora": "16:44",
          "fonte": "keyword",
          "data": "2026-03-12"
        }
      ]
    },
    "pranzo": {
      "gio": [
        {
          "ora": "12:22",
          "fonte": "gap+schermo",
          "data": "2026-03-12"
        }
      ]
    },
    "cena": {
      "mar": [
        {
          "ora": "20:18",
          "fonte": "gap+schermo",
          "data": "2026-03-17"
        }
      ]
    }
  },
  "ultimo_messaggio": "2026-03-19T15:33:40.000612",
  "stabilizzazioni_notificate": []
}